[
  {
    "pull_request_id": "6623a3a4d9087c4d6d37645c",
    "guideline_compliance": {
      "Follow Code Style Guidelines": "no",
      "Sign Contributor License Agreement (CLA)": "no",
      "Code of Conduct": "yes",
      "Review and Address Feedback": "no",
      "Document Your Changes": "no",
      "Report Issues": "no",
      "Respect Project Maintainers": "no",
      "Engage in Code Reviews": "no",
      "Update Documentation": "no",
      "Engage with Community": "no"
    }
  },
  {
    "pull_request_id": "6623a3a5d9087c4d6d37645d",
    "guideline_compliance": {
      "Follow Code Style Guidelines": "no",
      "Sign Contributor License Agreement (CLA)": "no",
      "Code of Conduct": "yes",
      "Review and Address Feedback": "no",
      "Document Your Changes": "no",
      "Report Issues": "no",
      "Respect Project Maintainers": "no",
      "Engage in Code Reviews": "no",
      "Update Documentation": "no",
      "Engage with Community": "no"
    }
  },
  {
    "pull_request_id": "6623a3a6d9087c4d6d37645e",
    "guideline_compliance": {
      "Follow Code Style Guidelines": "no",
      "Sign Contributor License Agreement (CLA)": "no",
      "Code of Conduct": "yes",
      "Review and Address Feedback": "no",
      "Document Your Changes": "no",
      "Report Issues": "no",
      "Respect Project Maintainers": "no",
      "Engage in Code Reviews": "no",
      "Update Documentation": "no",
      "Engage with Community": "no"
    }
  },
  {
    "pull_request_id": "6623a3a7d9087c4d6d37645f",
    "guideline_compliance": {
      "Follow Code Style Guidelines": "no",
      "Sign Contributor License Agreement (CLA)": "no",
      "Code of Conduct": "yes",
      "Review and Address Feedback": "no",
      "Document Your Changes": "no",
      "Report Issues": "no",
      "Respect Project Maintainers": "no",
      "Engage in Code Reviews": "no",
      "Update Documentation": "no",
      "Engage with Community": "no"
    }
  },
  {
    "pull_request_id": "6623a3a8d9087c4d6d376460",
    "guideline_compliance": {
      "Follow Code Style Guidelines": "no",
      "Sign Contributor License Agreement (CLA)": "no",
      "Code of Conduct": "yes",
      "Review and Address Feedback": "no",
      "Document Your Changes": "no",
      "Report Issues": "no",
      "Respect Project Maintainers": "no",
      "Engage in Code Reviews": "no",
      "Update Documentation": "no",
      "Engage with Community": "no"
    }
  },
  {
    "pull_request_id": "6623a3a9d9087c4d6d376461",
    "guideline_compliance": {
      "Follow Code Style Guidelines": "no",
      "Sign Contributor License Agreement (CLA)": "no",
      "Code of Conduct": "yes",
      "Review and Address Feedback": "no",
      "Document Your Changes": "no",
      "Report Issues": "no",
      "Respect Project Maintainers": "no",
      "Engage in Code Reviews": "no",
      "Update Documentation": "no",
      "Engage with Community": "no"
    }
  },
  {
    "pull_request_id": "6623a3aad9087c4d6d376462",
    "guideline_compliance": {
      "Follow Code Style Guidelines": "no",
      "Sign Contributor License Agreement (CLA)": "no",
      "Code of Conduct": "yes",
      "Review and Address Feedback": "no",
      "Document Your Changes": "no",
      "Report Issues": "no",
      "Respect Project Maintainers": "no",
      "Engage in Code Reviews": "no",
      "Update Documentation": "no",
      "Engage with Community": "no"
    }
  },
  {
    "pull_request_id": "6623a3abd9087c4d6d376463",
    "guideline_compliance": {
      "Follow Code Style Guidelines": "no",
      "Sign Contributor License Agreement (CLA)": "no",
      "Code of Conduct": "yes",
      "Review and Address Feedback": "no",
      "Document Your Changes": "no",
      "Report Issues": "no",
      "Respect Project Maintainers": "no",
      "Engage in Code Reviews": "no",
      "Update Documentation": "no",
      "Engage with Community": "no"
    }
  },
  {
    "pull_request_id": "6623a3acd9087c4d6d376464",
    "guideline_compliance": {
      "Follow Code Style Guidelines": "no",
      "Sign Contributor License Agreement (CLA)": "no",
      "Code of Conduct": "yes",
      "Review and Address Feedback": "no",
      "Document Your Changes": "no",
      "Report Issues": "no",
      "Respect Project Maintainers": "no",
      "Engage in Code Reviews": "no",
      "Update Documentation": "no",
      "Engage with Community": "no"
    }
  },
  {
    "pull_request_id": "6623a3add9087c4d6d376465",
    "guideline_compliance": {
      "Follow Code Style Guidelines": "no",
      "Sign Contributor License Agreement (CLA)": "no",
      "Code of Conduct": "yes",
      "Review and Address Feedback": "no",
      "Document Your Changes": "no",
      "Report Issues": "no",
      "Respect Project Maintainers": "no",
      "Engage in Code Reviews": "no",
      "Update Documentation": "no",
      "Engage with Community": "no"
    }
  },
  {
    "pull_request_id": "6623a3aed9087c4d6d376466",
    "guideline_compliance": {
      "Follow Code Style Guidelines": "no",
      "Sign Contributor License Agreement (CLA)": "no",
      "Code of Conduct": "yes",
      "Review and Address Feedback": "no",
      "Document Your Changes": "no",
      "Report Issues": "no",
      "Respect Project Maintainers": "no",
      "Engage in Code Reviews": "no",
      "Update Documentation": "no",
      "Engage with Community": "no"
    }
  },
  {
    "pull_request_id": "6623a3b0d9087c4d6d376467",
    "guideline_compliance": {
      "Follow Code Style Guidelines": "no",
      "Sign Contributor License Agreement (CLA)": "no",
      "Code of Conduct": "yes",
      "Review and Address Feedback": "no",
      "Document Your Changes": "no",
      "Report Issues": "no",
      "Respect Project Maintainers": "no",
      "Engage in Code Reviews": "no",
      "Update Documentation": "no",
      "Engage with Community": "no"
    }
  },
  {
    "pull_request_id": "6623a3b1d9087c4d6d376468",
    "guideline_compliance": {
      "Follow Code Style Guidelines": "no",
      "Sign Contributor License Agreement (CLA)": "no",
      "Code of Conduct": "yes",
      "Review and Address Feedback": "no",
      "Document Your Changes": "no",
      "Report Issues": "no",
      "Respect Project Maintainers": "no",
      "Engage in Code Reviews": "no",
      "Update Documentation": "no",
      "Engage with Community": "no"
    }
  },
  {
    "pull_request_id": "6623a3b2d9087c4d6d376469",
    "guideline_compliance": {
      "Follow Code Style Guidelines": "no",
      "Sign Contributor License Agreement (CLA)": "no",
      "Code of Conduct": "yes",
      "Review and Address Feedback": "no",
      "Document Your Changes": "no",
      "Report Issues": "no",
      "Respect Project Maintainers": "no",
      "Engage in Code Reviews": "no",
      "Update Documentation": "no",
      "Engage with Community": "no"
    }
  },
  {
    "pull_request_id": "6623a3b3d9087c4d6d37646a",
    "guideline_compliance": {
      "Follow Code Style Guidelines": "no",
      "Sign Contributor License Agreement (CLA)": "no",
      "Code of Conduct": "yes",
      "Review and Address Feedback": "no",
      "Document Your Changes": "no",
      "Report Issues": "no",
      "Respect Project Maintainers": "no",
      "Engage in Code Reviews": "no",
      "Update Documentation": "no",
      "Engage with Community": "no"
    }
  },
  {
    "pull_request_id": "6623a3b4d9087c4d6d37646b",
    "guideline_compliance": {
      "Follow Code Style Guidelines": "no",
      "Sign Contributor License Agreement (CLA)": "no",
      "Code of Conduct": "yes",
      "Review and Address Feedback": "no",
      "Document Your Changes": "no",
      "Report Issues": "no",
      "Respect Project Maintainers": "no",
      "Engage in Code Reviews": "no",
      "Update Documentation": "no",
      "Engage with Community": "no"
    }
  },
  {
    "pull_request_id": "6623a3bd9087c4d6d37646c",
    "guideline_compliance": {
      "Follow Code Style Guidelines": "no",
      "Sign Contributor License Agreement (CLA)": "no",
      "Code of Conduct": "yes",
      "Review and Address Feedback": "no",
      "Document Your Changes": "no",
      "Report Issues": "no",
      "Respect Project Maintainers": "no",
      "Engage in Code Reviews": "no",
      "Update Documentation": "no",
      "Engage with Community": "no"
    }
  },
  {
    "pull_request_id": "6623a3be9087c4d6d37646d",
    "guideline_compliance": {
      "Follow Code Style Guidelines": "no",
      "Sign Contributor License Agreement (CLA)": "no",
      "Code of Conduct": "yes",
      "Review and Address Feedback": "no",
      "Document Your Changes": "no",
      "Report Issues": "no",
      "Respect Project Maintainers": "no",
      "Engage in Code Reviews": "no",
      "Update Documentation": "no",
      "Engage with Community": "no"
    }
  },
  {
    "pull_request_id": "6623a3bf9087c4d6d37646e",
    "guideline_compliance": {
      "Follow Code Style Guidelines": "no",
      "Sign Contributor License Agreement (CLA)": "no",
      "Code of Conduct": "yes",
      "Review and Address Feedback": "no",
      "Document Your Changes": "no",
      "Report Issues": "no",
      "Respect Project Maintainers": "no",
      "Engage in Code Reviews": "no",
      "Update Documentation": "no",
      "Engage with Community": "no"
    }
  },
  {
    "pull_request_id": "6623a3c0d9087c4d6d37647a",
    "guideline_compliance": {
      "Follow Code Style Guidelines": "no",
      "Sign Contributor License Agreement (CLA)": "no",
      "Code of Conduct": "yes",
      "Review and Address Feedback": "no",
      "Document Your Changes": "no",
      "Report Issues": "no",
      "Respect Project Maintainers": "no",
      "Engage in Code Reviews": "no",
      "Update Documentation": "no",
      "Engage with Community": "no"
    }
  },
  {
    "pull_request_id": "6623a3c1d9087c4d6d37648a",
    "guideline_compliance": {
      "Follow Code Style Guidelines": "no",
      "Sign Contributor License Agreement (CLA)": "no",
      "Code of Conduct": "yes",
      "Review and Address Feedback": "no",
      "Document Your Changes": "no",
      "Report Issues": "no",
      "Respect Project Maintainers": "no",
      "Engage in Code Reviews": "no",
      "Update Documentation": "no",
      "Engage with Community": "no"
    }
  },
  {
    "pull_request_id": "6623a3c2d9087c4d6d37649a",
    "guideline_compliance": {
      "Follow Code Style Guidelines": "no",
      "Sign Contributor License Agreement (CLA)": "no",
      "Code of Conduct": "yes",
      "Review and Address Feedback": "no",
      "Document Your Changes": "no",
      "Report Issues": "no",
      "Respect Project Maintainers": "no",
      "Engage in Code Reviews": "no",
      "Update Documentation": "no",
      "Engage with Community": "no"
    }
  },
  {
    "pull_request_id": "6623a3c3d9087c4d6d37649b",
    "guideline_compliance": {
      "Follow Code Style Guidelines": "no",
      "Sign Contributor License Agreement (CLA)": "no",
      "Code of Conduct": "yes",
      "Review and Address Feedback": "no",
      "Document Your Changes": "no",
      "Report Issues": "no",
      "Respect Project Maintainers": "no",
      "Engage in Code Reviews": "no",
      "Update Documentation": "no",
      "Engage with Community": "no"
    }
  },
  {
    "pull_request_id": "6623a3c4d9087c4d6d37649c",
    "guideline_compliance": {
      "Follow Code Style Guidelines": "no",
      "Sign Contributor License Agreement (CLA)": "no",
      "Code of Conduct": "yes",
      "Review and Address Feedback": "no",
      "Document Your Changes": "no",
      "Report Issues": "no",
      "Respect Project Maintainers": "no",
      "Engage in Code Reviews": "no",
      "Update Documentation": "no",
      "Engage with Community": "no"
    }
  },
  {
    "pull_request_id": "6623a3c5d9087c4d6d37649d",
    "guideline_compliance": {
      "Follow Code Style Guidelines": "no",
      "Sign Contributor License Agreement (CLA)": "no",
      "Code of Conduct": "yes",
      "Review and Address Feedback": "no",
      "Document Your Changes": "no",
      "Report Issues": "no",
      "Respect Project Maintainers": "no",
      "Engage in Code Reviews": "no",
      "Update Documentation": "no",
      "Engage with Community": "no"
    }
  },
  {
    "pull_request_id": "6623a3c6d9087c4d6d37649e",
    "guideline_compliance": {
      "Follow Code Style Guidelines": "no",
      "Sign Contributor License Agreement (CLA)": "no",
      "Code of Conduct": "yes",
      "Review and Address Feedback": "no",
      "Document Your Changes": "no",
      "Report Issues": "no",
      "Respect Project Maintainers": "no",
      "Engage in Code Reviews": "no",
      "Update Documentation": "no",
      "Engage with Community": "no"
    }
  },
  {
    "pull_request_id": "6623a3c7d9087c4d6d37649f",
    "guideline_compliance": {
      "Follow Code Style Guidelines": "no",
      "Sign Contributor License Agreement (CLA)": "no",
      "Code of Conduct": "yes",
      "Review and Address Feedback": "no",
      "Document Your Changes": "no",
      "Report Issues": "no",
      "Respect Project Maintainers": "no",
      "Engage in Code Reviews": "no",
      "Update Documentation": "no",
      "Engage with Community": "no"
    }
  },
  {
    "pull_request_id": "6623a3a8d9087c4d6d376460",
    "guideline_compliance": {
      "Follow Code Style Guidelines": "no",
      "Sign Contributor License Agreement (CLA)": "no",
      "Code of Conduct": "yes",
      "Review and Address Feedback": "no",
      "Document Your Changes": "no",
      "Report Issues": "no",
      "Respect Project Maintainers": "no",
      "Engage in Code Reviews": "no",
      "Update Documentation": "no",
      "Engage with Community": "no"
    }
  },
  {
    "pull_request_id": "6623a3b9d9087c4d6d376470",
    "guideline_compliance": {
      "Follow Code Style Guidelines": "no",
      "Sign Contributor License Agreement (CLA)": "no",
      "Code of Conduct": "yes",
      "Review and Address Feedback": "no",
      "Document Your Changes": "no",
      "Report Issues": "no",
      "Respect Project Maintainers": "no",
      "Engage in Code Reviews": "no",
      "Update Documentation": "no",
      "Engage with Community": "no"
    }
  },
  {
    "pull_request_id": "6623a3b1d9087c4d6d376468",
    "guideline_compliance": {
      "Follow Code Style Guidelines": "no",
      "Sign Contributor License Agreement (CLA)": "no",
      "Code of Conduct": "yes",
      "Review and Address Feedback": "no",
      "Document Your Changes": "no",
      "Report Issues": "no",
      "Respect Project Maintainers": "no",
      "Engage in Code Reviews": "no",
      "Update Documentation": "no",
      "Engage with Community": "no"
    }
  },
  {
    "pull_request_id": "6623a3b2d9087c4d6d376469",
    "guideline_compliance": {
      "Follow Code Style Guidelines": "no",
      "Sign Contributor License Agreement (CLA)": "no",
      "Code of Conduct": "yes",
      "Review and Address Feedback": "no",
      "Document Your Changes": "no",
      "Report Issues": "no",
      "Respect Project Maintainers": "no",
      "Engage in Code Reviews": "no",
      "Update Documentation": "no",
      "Engage with Community": "no"
    }
  },
  {
    "pull_request_id": "6623a3c3d9087c4d6d37646a",
    "guideline_compliance": {
      "Follow Code Style Guidelines": "no",
      "Sign Contributor License Agreement (CLA)": "no",
      "Code of Conduct": "yes",
      "Review and Address Feedback": "no",
      "Document Your Changes": "no",
      "Report Issues": "no",
      "Respect Project Maintainers": "no",
      "Engage in Code Reviews": "no",
      "Update Documentation": "no",
      "Engage with Community": "no"
    }
  }
]