[
  {
    "pull_request_id": "661c917f3a92c11966e2fc7b",
    "guideline_compliance": {
      "Follow Code Style Guidelines": "no",
      "Sign Contributor License Agreement (CLA)": "no",
      "Code of Conduct": "no",
      "Review and Address Feedback": "no",
      "Document Your Changes": "no",
      "Report Issues": "no",
      "Respect Project Maintainers": "no",
      "Engage in Code Reviews": "no",
      "Update Documentation": "no",
      "Engage with Community": "no"
    }
  },
  {
    "pull_request_id": "661c91813a92c11966e2fc7c",
    "guideline_compliance": {
      "Follow Code Style Guidelines": "no",
      "Sign Contributor License Agreement (CLA)": "no",
      "Code of Conduct": "no",
      "Review and Address Feedback": "no",
      "Document Your Changes": "no",
      "Report Issues": "no",
      "Respect Project Maintainers": "no",
      "Engage in Code Reviews": "no",
      "Update Documentation": "no",
      "Engage with Community": "no"
    }
  },
  {
    "pull_request_id": "661c91823a92c11966e2fc7d",
    "guideline_compliance": {
      "Follow Code Style Guidelines": "no",
      "Sign Contributor License Agreement (CLA)": "no",
      "Code of Conduct": "no",
      "Review and Address Feedback": "no",
      "Document Your Changes": "no",
      "Report Issues": "no",
      "Respect Project Maintainers": "no",
      "Engage in Code Reviews": "no",
      "Update Documentation": "no",
      "Engage with Community": "no"
    }
  }
]